{
  "formatVersion": 1,
  "database": {
    "version": 1,
    "identityHash": "1f1fa9d3716779a2ba3e7650d3250975",
    "entities": [
      {
        "tableName": "books",
        "createSql": "CREATE TABLE IF NOT EXISTS `${TABLE_NAME}` (`id` INTEGER PRIMARY KEY AUTOINCREMENT NOT NULL, `title` TEXT NOT NULL, `price` REAL NOT NULL, `categoryId` INTEGER NOT NULL, `author` TEXT)",
        "fields": [
          {
            "fieldPath": "id",
            "columnName": "id",
            "affinity": "INTEGER",
            "notNull": true
          },
          {
            "fieldPath": "title",
            "columnName": "title",
            "affinity": "TEXT",
            "notNull": true
          },
          {
            "fieldPath": "price",
            "columnName": "price",
            "affinity": "REAL",
            "notNull": true
          },
          {
            "fieldPath": "categoryId",
            "columnName": "categoryId",
            "affinity": "INTEGER",
            "notNull": true
          },
          {
            "fieldPath": "author",
            "columnName": "author",
            "affinity": "TEXT",
            "notNull": false
          }
        ],
        "primaryKey": {
          "autoGenerate": true,
          "columnNames": [
            "id"
          ]
        },
        "indices": [],
        "foreignKeys": []
      }
    ],
    "views": [],
    "setupQueries": [
      "CREATE TABLE IF NOT EXISTS room_master_table (id INTEGER PRIMARY KEY,identity_hash TEXT)",
      "INSERT OR REPLACE INTO room_master_table (id,identity_hash) VALUES(42, '1f1fa9d3716779a2ba3e7650d3250975')"
    ]
  }
}